ThreeWToolkit/README.md
ThreeWToolkit/__init__.py
ThreeWToolkit/constants.py
ThreeWToolkit/pipeline.py
ThreeWToolkit/assessment/__init__.py
ThreeWToolkit/assessment/assessment_visualizations.py
ThreeWToolkit/assessment/model_assess.py
ThreeWToolkit/core/__init__.py
ThreeWToolkit/core/base_assessment.py
ThreeWToolkit/core/base_assessment_visualization.py
ThreeWToolkit/core/base_dataset.py
ThreeWToolkit/core/base_feature_extractor.py
ThreeWToolkit/core/base_metrics.py
ThreeWToolkit/core/base_model_trainer.py
ThreeWToolkit/core/base_models.py
ThreeWToolkit/core/base_preprocessing.py
ThreeWToolkit/core/base_step.py
ThreeWToolkit/core/base_time_series_holdout.py
ThreeWToolkit/core/enums.py
ThreeWToolkit/data_loader/__init__.py
ThreeWToolkit/data_loader/csv_data_loader.py
ThreeWToolkit/data_visualization/__init__.py
ThreeWToolkit/data_visualization/base_visualizer.py
ThreeWToolkit/data_visualization/correlation_heatmap.py
ThreeWToolkit/data_visualization/plot_fft.py
ThreeWToolkit/data_visualization/plot_multiple_series.py
ThreeWToolkit/data_visualization/plot_series.py
ThreeWToolkit/data_visualization/plot_utils.py
ThreeWToolkit/data_visualization/plots.py
ThreeWToolkit/data_visualization/seasonal_decomposition.py
ThreeWToolkit/data_visualization/three_w_chart.py
ThreeWToolkit/data_visualization/wavelet_spectrogram.py
ThreeWToolkit/dataset/__init__.py
ThreeWToolkit/dataset/parquet_dataset.py
ThreeWToolkit/feature_extraction/__init__.py
ThreeWToolkit/feature_extraction/extract_exponential_statistics_features.py
ThreeWToolkit/feature_extraction/extract_statistical_features.py
ThreeWToolkit/feature_extraction/extract_wavelet_features.py
ThreeWToolkit/metrics/__init__.py
ThreeWToolkit/metrics/_classification.py
ThreeWToolkit/metrics/_regression.py
ThreeWToolkit/models/__init__.py
ThreeWToolkit/models/mlp.py
ThreeWToolkit/models/sklearn_models.py
ThreeWToolkit/preprocessing/__init__.py
ThreeWToolkit/preprocessing/_data_processing.py
ThreeWToolkit/reports/__init__.py
threewtoolkit-1.0.3.dist-info/licenses/LICENSE.md
threewtoolkit-1.0.3.dist-info/METADATA
threewtoolkit-1.0.3.dist-info/WHEEL
threewtoolkit-1.0.3.dist-info/top_level.txt
threewtoolkit-1.0.3.dist-info/RECORD
