Metadata-Version: 2.4
Name: ThreeWToolkit
Version: 1.0.3
Summary: A modular and open-source AI toolkit for time-series processing, aimed at fault detection and classification in oil well operation
Author-email: Ricardo Emanuel Vaz Vargas <ricardo.vargas@petrobras.com.br>
License: Apache-2.0
Project-URL: Homepage, https://github.com/petrobras/3W
Project-URL: Repository, https://github.com/petrobras/3W
Project-URL: Documentation, https://github.com/petrobras/3W
Project-URL: Bug Tracker, https://github.com/petrobras/3W/issues
Project-URL: Source Code, https://github.com/petrobras/3W
Project-URL: Changelog, https://github.com/petrobras/3W/releases
Keywords: machine-learning,time-series,fault-detection,oil-wells,classification,petroleum,data-science,artificial-intelligence
Requires-Python: >=3.10
License-File: LICENSE.md
Requires-Dist: numpy>=1.26.4
Requires-Dist: scipy>=1.15.2
Requires-Dist: pandas>=2.2.3
Requires-Dist: scikit-learn>=1.6.1
Requires-Dist: matplotlib>=3.10.1
Requires-Dist: seaborn>=0.13.2
Requires-Dist: plotly>=6.0.0
Requires-Dist: imbalanced-learn>=0.13.0
Requires-Dist: ipykernel>=6.29.5
Requires-Dist: ipywidgets==8.1.7
Requires-Dist: jupyter-client==8.6.3
Requires-Dist: jupyter-core==5.8.1
Requires-Dist: Pillow>=11.0.0
Requires-Dist: scikit-image>=0.25.2
Requires-Dist: torch>=2.7.0
Requires-Dist: torchvision>=0.22.0
Requires-Dist: torchmetrics>=1.6.2
Requires-Dist: timm>=1.0.15
Requires-Dist: tqdm>=4.67.1
Requires-Dist: pydantic>=2.11
Requires-Dist: PyWavelets>=1.8.0
Requires-Dist: pyarrow>=20.0.0
Requires-Dist: pylatex>=1.4.2
Requires-Dist: statsmodels>=0.14.5
Requires-Dist: requests<=2.35.5
Provides-Extra: dev
Requires-Dist: black>=25.9.0; extra == "dev"
Requires-Dist: mypy>=1.16.0; extra == "dev"
Requires-Dist: flake8; extra == "dev"
Requires-Dist: jupyter; extra == "dev"
Requires-Dist: ruff>=0.12.2; extra == "dev"
Requires-Dist: uv; extra == "dev"
Requires-Dist: types-requests>=2.32.4.20250611; extra == "dev"
Requires-Dist: coverage>=7.8.1; extra == "dev"
Requires-Dist: pytest>=8.3.5; extra == "dev"
Requires-Dist: pytest-mock>=3.14.1; extra == "dev"
Provides-Extra: docs
Requires-Dist: mkdocs; extra == "docs"
Requires-Dist: mkdocstrings[python]; extra == "docs"
Requires-Dist: sphinx; extra == "docs"
Dynamic: license-file
